CHANGES.txt
LICENSE.txt
MANIFEST.in
README.txt
setup.py
setupinfo.py
unittests.py
docs/README_DOCS.txt
examples/__init__.py
examples/dates.py
examples/engines.py
examples/inserts.py
examples/microseconds.py
examples/multi_resultsets.py
examples/mysql_warnings.py
examples/prepared_statements.py
examples/transaction.py
examples/unicode.py
examples/warnings.py
lib/__init__.py
lib/cpy_distutils.py
lib/mysql/__init__.py
lib/mysql/connector/__init__.py
lib/mysql/connector/abstracts.py
lib/mysql/connector/authentication.py
lib/mysql/connector/catch23.py
lib/mysql/connector/charsets.py
lib/mysql/connector/connection.py
lib/mysql/connector/connection_cext.py
lib/mysql/connector/constants.py
lib/mysql/connector/conversion.py
lib/mysql/connector/cursor.py
lib/mysql/connector/cursor_cext.py
lib/mysql/connector/custom_types.py
lib/mysql/connector/dbapi.py
lib/mysql/connector/errorcode.py
lib/mysql/connector/errors.py
lib/mysql/connector/network.py
lib/mysql/connector/optionfiles.py
lib/mysql/connector/pooling.py
lib/mysql/connector/protocol.py
lib/mysql/connector/utils.py
lib/mysql/connector/version.py
lib/mysql/connector/django/__init__.py
lib/mysql/connector/django/base.py
lib/mysql/connector/django/client.py
lib/mysql/connector/django/compiler.py
lib/mysql/connector/django/creation.py
lib/mysql/connector/django/features.py
lib/mysql/connector/django/introspection.py
lib/mysql/connector/django/operations.py
lib/mysql/connector/django/schema.py
lib/mysql/connector/django/validation.py
lib/mysql/connector/fabric/__init__.py
lib/mysql/connector/fabric/balancing.py
lib/mysql/connector/fabric/caching.py
lib/mysql/connector/fabric/connection.py
lib/mysql/connector/locales/__init__.py
lib/mysql/connector/locales/eng/__init__.py
lib/mysql/connector/locales/eng/client_error.py
lib/mysql_connector.egg-info/PKG-INFO
lib/mysql_connector.egg-info/SOURCES.txt
lib/mysql_connector.egg-info/dependency_links.txt
lib/mysql_connector.egg-info/top_level.txt
src/exceptions.c
src/force_cpp_linkage.cc
src/mysql_capi.c
src/mysql_capi_conversion.c
src/mysql_connector.c
src/include/catch23.h
src/include/exceptions.h
src/include/mysql_capi.h
